[
  {
    "name": "createdAt",
    "fieldId": "createdAt",
    "componentId": "date",
    "options": {},
    "validations": {
      "required-field": {
        "value": true
      }
    },
    "fieldType": "date",
    "system": true,
    "defaultField": false,
    "modelId": "menu"
  },
  {
    "name": "updatedAt",
    "fieldId": "updatedAt",
    "componentId": "date",
    "options": {},
    "validations": {
      "required-field": {
        "value": true
      }
    },
    "fieldType": "date",
    "system": true,
    "defaultField": false,
    "modelId": "menu"
  },
  {
    "name": "ID",
    "fieldId": "ID",
    "componentId": "single-line-text",
    "options": {},
    "validations": {
      "required-field": {
        "value": true
      }
    },
    "fieldType": "string",
    "system": true,
    "defaultField": false,
    "modelId": "menu"
  },
  {
    "name": "status",
    "fieldId": "status",
    "componentId": "single-line-text",
    "options": {},
    "validations": {
      "required-field": {
        "value": true
      }
    },
    "fieldType": "string",
    "system": true,
    "defaultField": false,
    "modelId": "menu"
  },
  {
    "name": "libelle",
    "description": "Libellé",
    "fieldId": "libelle",
    "modelId": "menu",
    "componentId": "single-line-text",
    "options": {},
    "validations": {},
    "fieldType": "string"
  },
  {
    "name": "internal_url",
    "description": "Lien interne",
    "fieldId": "internal_url",
    "modelId": "menu",
    "componentId": "slug",
    "options": {},
    "validations": {},
    "fieldType": "string"
  },
  {
    "name": "external_url",
    "description": "Lien Externe",
    "fieldId": "external_url",
    "modelId": "menu",
    "componentId": "url",
    "options": {},
    "validations": {},
    "fieldType": "string"
  }
]